README.md
setup.cfg
setup.py
tests/__init__.py
tests/test_momentums.py
tests/test_trends.py
tests/test_utilities.py
tests/test_volatilities.py
tests/test_volumes.py
ttrpy/__init__.py
ttrpy.egg-info/PKG-INFO
ttrpy.egg-info/SOURCES.txt
ttrpy.egg-info/dependency_links.txt
ttrpy.egg-info/requires.txt
ttrpy.egg-info/top_level.txt
ttrpy/momentum/__init__.py
ttrpy/momentum/apo.py
ttrpy/momentum/mfi.py
ttrpy/momentum/mom.py
ttrpy/momentum/ppo.py
ttrpy/momentum/roc.py
ttrpy/momentum/rocr.py
ttrpy/momentum/rsi.py
ttrpy/momentum/stoch.py
ttrpy/momentum/stochf.py
ttrpy/momentum/ultosc.py
ttrpy/momentum/willr.py
ttrpy/trend/__init__.py
ttrpy/trend/aroon.py
ttrpy/trend/aroonosc.py
ttrpy/trend/bop.py
ttrpy/trend/cci.py
ttrpy/trend/dema.py
ttrpy/trend/ema.py
ttrpy/trend/kama.py
ttrpy/trend/macd.py
ttrpy/trend/macdext.py
ttrpy/trend/sma.py
ttrpy/trend/t3.py
ttrpy/trend/tema.py
ttrpy/trend/trima.py
ttrpy/trend/trix.py
ttrpy/trend/wma.py
ttrpy/util/__init__.py
ttrpy/util/midpnt.py
ttrpy/util/midpri.py
ttrpy/util/trange.py
ttrpy/volatility/__init__.py
ttrpy/volatility/atr.py
ttrpy/volatility/bbands.py
ttrpy/volatility/natr.py
ttrpy/volume/__init__.py
ttrpy/volume/ad.py
ttrpy/volume/adosc.py
ttrpy/volume/obv.py